mcu/__init__.py
squad_foundries_plugins-1.3.dist-info/LICENSE
squad_foundries_plugins-1.3.dist-info/METADATA
squad_foundries_plugins-1.3.dist-info/WHEEL
squad_foundries_plugins-1.3.dist-info/entry_points.txt
squad_foundries_plugins-1.3.dist-info/top_level.txt
squad_foundries_plugins-1.3.dist-info/RECORD
